django_discount/__init__.py
django_discount/admin.py
django_discount/apps.py
django_discount/consts.py
django_discount/models.py
django_discount/settings.py
django_discount/signals.py
django_discount/utils.py
django_discount/views.py
django_discount/locale/fa/LC_MESSAGES/django.mo
django_discount/locale/fa/LC_MESSAGES/django.po
django_discount/migrations/0001_initial.py
django_discount/migrations/0002_auto_20201201_1425.py
django_discount/migrations/0003_auto_20201202_0203.py
django_discount/migrations/0004_auto_20201202_0229.py
django_discount/migrations/__init__.py
django_discount-0.0.3.dist-info/LICENSE
django_discount-0.0.3.dist-info/METADATA
django_discount-0.0.3.dist-info/WHEEL
django_discount-0.0.3.dist-info/top_level.txt
django_discount-0.0.3.dist-info/RECORD
