Metadata-Version: 2.1
Name: django-discount
Version: 0.0.3
Summary: A Django App for handling creating dynamic discount system.
Home-page: https://github.com/Execut3/django-discount
Author: Execut3
Author-email: execut3.binarycodes@gmail.com
License: GPT
Platform: UNKNOWN
Requires-Dist: Django (>=2.0)
